[
  {
    "id": 423,
    "object": "radical",
    "url": "https://api.wanikani.com/v2/subjects/423",
    "level": 55,
    "characters": "感",
    "meanings": [
      "Feeling"
    ],
    "readings": [],
    "examples": [],
    "radical_to_kanji": [
      2279
    ],
    "meaning_mnemonic": "This radical is the same as the kanji. It means <radical>feeling</radical>.",
    "reading_mnemonic": "",
    "kanji_to_vocab": [
      2279
    ],
    "radical_from_kanji": [],
    "part_of_speech": [],
    "kanji_from_vocab": [],
    "vocab_to_kanji_info": [],
    "kanji_to_vocab_info": []
  },
  {
    "id": 8832,
    "object": "radical",
    "url": "https://api.wanikani.com/v2/subjects/8832",
    "level": 55,
    "characters": "疑",
    "meanings": [
      "Doubt"
    ],
    "readings": [],
    "examples": [],
    "radical_to_kanji": [
      2283,
      2416
    ],
    "meaning_mnemonic": "This radical is the same as the kanji. It means <radical>doubt</radical>.",
    "reading_mnemonic": "",
    "kanji_to_vocab": [
      2283,
      2416
    ],
    "radical_from_kanji": [],
    "part_of_speech": [],
    "kanji_from_vocab": [],
    "vocab_to_kanji_info": [],
    "kanji_to_vocab_info": []
  }
]